ddmail_webapp/__init__.py
ddmail_webapp/auth.py
ddmail_webapp/forms.py
ddmail_webapp/models.py
ddmail_webapp/settings.py
ddmail_webapp/unauthenticated.py
ddmail_webapp/well_known.py
ddmail_webapp/static/contact_general_pubkey.asc
ddmail_webapp/static/contact_legal_pubkey.asc
ddmail_webapp/static/contact_security_pubkey.asc
ddmail_webapp/static/contact_support_pubkey.asc
ddmail_webapp/static/mta-sts.txt
ddmail_webapp/static/robots.txt
ddmail_webapp/static/security.txt
ddmail_webapp/static/sitemap.xml
ddmail_webapp/static/css/style.css
ddmail_webapp/templates/about.html
ddmail_webapp/templates/account_domain_demand.html
ddmail_webapp/templates/all.html
ddmail_webapp/templates/contact.html
ddmail_webapp/templates/help.html
ddmail_webapp/templates/login.html
ddmail_webapp/templates/main.html
ddmail_webapp/templates/message.html
ddmail_webapp/templates/pricing_and_payment.html
ddmail_webapp/templates/register.html
ddmail_webapp/templates/settings.html
ddmail_webapp/templates/settings_activate_openpgp_encryption.html
ddmail_webapp/templates/settings_add_alias.html
ddmail_webapp/templates/settings_add_domain.html
ddmail_webapp/templates/settings_add_email.html
ddmail_webapp/templates/settings_add_user_to_account.html
ddmail_webapp/templates/settings_added_user_to_account.html
ddmail_webapp/templates/settings_change_key_on_user.html
ddmail_webapp/templates/settings_change_password_on_email.html
ddmail_webapp/templates/settings_change_password_on_user.html
ddmail_webapp/templates/settings_deactivate_openpgp_encryption.html
ddmail_webapp/templates/settings_menu.html
ddmail_webapp/templates/settings_payment.html
ddmail_webapp/templates/settings_payment_token.html
ddmail_webapp/templates/settings_remove_account_user.html
ddmail_webapp/templates/settings_remove_alias.html
ddmail_webapp/templates/settings_remove_domain.html
ddmail_webapp/templates/settings_remove_email.html
ddmail_webapp/templates/settings_remove_openpgp_public_key.html
ddmail_webapp-0.0.9.dist-info/METADATA
ddmail_webapp-0.0.9.dist-info/WHEEL
ddmail_webapp-0.0.9.dist-info/licenses/LICENSE
ddmail_webapp-0.0.9.dist-info/RECORD
