Metadata-Version: 2.4
Name: ddmail_webapp
Version: 0.0.9
Summary: Main web application for the DDMail project.
Project-URL: Homepage, https://github.com/drzobin/ddmail_webapp
Project-URL: Issues, https://github.com/drzobin/ddmail_webapp/issues
Author-email: Robin Larsson <me@drz.se>
License-Expression: AGPL-3.0
License-File: LICENSE
Classifier: Operating System :: POSIX :: Linux
Classifier: Programming Language :: Python :: 3
Requires-Python: >=3.8
Requires-Dist: argon2-cffi
Requires-Dist: ddmail-validators
Requires-Dist: dnspython
Requires-Dist: flask
Requires-Dist: flask-session
Requires-Dist: flask-sqlalchemy
Requires-Dist: flask-wtf
Requires-Dist: gunicorn
Requires-Dist: mysqlclient
Requires-Dist: requests
Requires-Dist: toml
Provides-Extra: dev
Requires-Dist: argon2-cffi; extra == 'dev'
Requires-Dist: ddmail-validators; extra == 'dev'
Requires-Dist: dnspython; extra == 'dev'
Requires-Dist: flask; extra == 'dev'
Requires-Dist: flask-session; extra == 'dev'
Requires-Dist: flask-sqlalchemy; extra == 'dev'
Requires-Dist: flask-wtf; extra == 'dev'
Requires-Dist: gunicorn; extra == 'dev'
Requires-Dist: hatchling; extra == 'dev'
Requires-Dist: mysqlclient; extra == 'dev'
Requires-Dist: pyright; extra == 'dev'
Requires-Dist: pytest-cov; extra == 'dev'
Requires-Dist: requests; extra == 'dev'
Requires-Dist: ruff; extra == 'dev'
Requires-Dist: toml; extra == 'dev'
Requires-Dist: twine; extra == 'dev'
Provides-Extra: test
Requires-Dist: argon2-cffi; extra == 'test'
Requires-Dist: ddmail-validators; extra == 'test'
Requires-Dist: dnspython; extra == 'test'
Requires-Dist: flask; extra == 'test'
Requires-Dist: flask-session; extra == 'test'
Requires-Dist: flask-sqlalchemy; extra == 'test'
Requires-Dist: flask-wtf; extra == 'test'
Requires-Dist: gunicorn; extra == 'test'
Requires-Dist: mysqlclient; extra == 'test'
Requires-Dist: pytest-cov; extra == 'test'
Requires-Dist: requests; extra == 'test'
Requires-Dist: toml; extra == 'test'
